vulcan/__init__.py
vulcan/_account.py
vulcan/_api.py
vulcan/_api_helper.py
vulcan/_client.py
vulcan/_data.py
vulcan/_endpoints.py
vulcan/_exceptions.py
vulcan/_keystore.py
vulcan/_request_signer.py
vulcan/_utils.py
vulcan/data/__init__.py
vulcan/data/_addressbook.py
vulcan/data/_attendance.py
vulcan/data/_exam.py
vulcan/data/_grade.py
vulcan/data/_homework.py
vulcan/data/_lesson.py
vulcan/data/_lucky_number.py
vulcan/data/_message.py
vulcan/model/__init__.py
vulcan/model/_attachment.py
vulcan/model/_datetime.py
vulcan/model/_messagebox.py
vulcan/model/_period.py
vulcan/model/_pupil.py
vulcan/model/_school.py
vulcan/model/_serializable.py
vulcan/model/_student.py
vulcan/model/_subject.py
vulcan/model/_teacher.py
vulcan/model/_team.py
vulcan/model/_timeslot.py
vulcan/model/_unit.py
vulcan_api-2.4.2.dist-info/LICENSE
vulcan_api-2.4.2.dist-info/METADATA
vulcan_api-2.4.2.dist-info/WHEEL
vulcan_api-2.4.2.dist-info/top_level.txt
vulcan_api-2.4.2.dist-info/RECORD
