Metadata-Version: 2.2
Name: vulcan-api
Version: 2.4.2
Summary: Nieoficjalne API do dzienniczka elektronicznego UONET+
Home-page: https://github.com/kapi2289/vulcan-api
Author: Kacper Ziubryniewicz
Author-email: kapi2289@gmail.com
License: MIT
Project-URL: Documentation, https://vulcan-api.readthedocs.io/
Keywords: Vulcan,UONET+,Dzienniczek+,API,e-dziennik,hebe
Classifier: Development Status :: 5 - Production/Stable
Classifier: Intended Audience :: Developers
Classifier: License :: OSI Approved :: MIT License
Classifier: Natural Language :: Polish
Classifier: Operating System :: OS Independent
Classifier: Programming Language :: Python
Classifier: Programming Language :: Python :: 3.11
Classifier: Programming Language :: Python :: 3.12
Classifier: Topic :: Education
Classifier: Topic :: Internet :: WWW/HTTP :: Dynamic Content
Classifier: Topic :: Software Development :: Libraries :: Python Modules
Requires-Python: >=3.6,<4.0
License-File: LICENSE
Requires-Dist: pyopenssl
Requires-Dist: uonet-request-signer-hebe
Requires-Dist: pytz
Requires-Dist: aenum
Requires-Dist: related-without-future
Requires-Dist: aiohttp
Requires-Dist: faust-cchardet
Requires-Dist: aiodns
Requires-Dist: yarl
Provides-Extra: testing
Requires-Dist: pytest; extra == "testing"
Requires-Dist: python-dotenv; extra == "testing"
Dynamic: author
Dynamic: author-email
Dynamic: classifier
Dynamic: description
Dynamic: description-content-type
Dynamic: home-page
Dynamic: keywords
Dynamic: license
Dynamic: project-url
Dynamic: provides-extra
Dynamic: requires-dist
Dynamic: requires-python
Dynamic: summary
